<env:envelope xmlns:env="http://exist-db.org/data/envelope">
	<env:headers>
		<env:id>Concept-gasToDustRatio</env:id>
		<env:glossaryName>IVOAT</env:glossaryName>
		<env:timestamp>2019-12-10T10:35:29.29-05:00</env:timestamp>
	</env:headers>
	<env:instance>
		<skosxl:Concept xmlns:skosxl="http://www.w3.org/2008/05/skos#"
			xmlns:rdf="http://www.w3.org/1999/02/22-rdf-syntax-ns#" rdf:about="#gasToDustRatio">
			<skosxl:inScheme rdf:resource=""/>
			<skosxl:prefLabel>gas to dust ratio</skosxl:prefLabel>
			<skosxl:definition>gas to dust ratio</skosxl:definition>
			<skosxl:related rdf:resource="#dust"/>
			<skosxl:related rdf:resource="#gas"/>
			<skosxl:related rdf:resource="#interstellarReddening"/>
			<skosxl:related rdf:resource="#reddeningLaw"/>
			<skosxl:related rdf:resource="#selectiveAbsorption"/>
		</skosxl:Concept>
	</env:instance>
</env:envelope>
