<?xml version="1.0" encoding="UTF-8"?>
<env:envelope xmlns:env="http://marklogic.com/data-hub/envelope"><env:headers><env:id>01271f88-b2e3-4741-a71f-88b2e3074185</env:id><env:glossaryName>IVOAT</env:glossaryName><env:timestamp>2019-09-23T20:54:46.878-04:00</env:timestamp></env:headers><env:instance><skos:Concept xmlns:rdf="http://www.w3.org/1999/02/22-rdf-syntax-ns#" xmlns:skos="http://www.w3.org/2008/05/skos#" rdf:about="#opticalFilm">
		<skos:inScheme rdf:resource=""/>
		<skos:prefLabel>optical film</skos:prefLabel>
		<skos:definition>optical film</skos:definition>
		<skos:altLabel>film [optical]</skos:altLabel>
		<skos:narrower rdf:resource="#antireflectionCoating"/>
		<skos:narrower rdf:resource="#thinFilm"/>
		<skos:related rdf:resource="#dichroicMirror"/>
		<skos:related rdf:resource="#interferenceFilter"/>
		<skos:related rdf:resource="#lightInterference"/>
	</skos:Concept></env:instance></env:envelope>