<?xml version="1.0" encoding="UTF-8"?>
<env:envelope xmlns:env="http://marklogic.com/data-hub/envelope"><env:headers><env:id>1c66bb49-6c80-4400-a6bb-496c80540056</env:id><env:glossaryName>IVOAT</env:glossaryName><env:timestamp>2019-09-23T20:54:46.878-04:00</env:timestamp></env:headers><env:instance><skos:Concept xmlns:rdf="http://www.w3.org/1999/02/22-rdf-syntax-ns#" xmlns:skos="http://www.w3.org/2008/05/skos#" rdf:about="#radiationDamping">
		<skos:inScheme rdf:resource=""/>
		<skos:prefLabel>radiation damping</skos:prefLabel>
		<skos:definition>radiation damping</skos:definition>
		<skos:related rdf:resource="#dampingConstant"/>
		<skos:related rdf:resource="#decayOscillation"/>
		<skos:related rdf:resource="#radiativeBraking"/>
	</skos:Concept></env:instance></env:envelope>