<?xml version="1.0" encoding="UTF-8"?>
<env:envelope xmlns:env="http://marklogic.com/data-hub/envelope"><env:headers><env:id>4740b556-ab47-4f79-80b5-56ab470f79c4</env:id><env:glossaryName>IVOAT</env:glossaryName><env:timestamp>2019-09-23T20:54:46.878-04:00</env:timestamp></env:headers><env:instance><skos:Concept xmlns:rdf="http://www.w3.org/1999/02/22-rdf-syntax-ns#" xmlns:skos="http://www.w3.org/2008/05/skos#" rdf:about="#beamSwitching">
		<skos:inScheme rdf:resource=""/>
		<skos:prefLabel>beam switching</skos:prefLabel>
		<skos:definition>beam switching</skos:definition>
		<skos:related rdf:resource="#radioTelescope"/>
	</skos:Concept></env:instance></env:envelope>