<?xml version="1.0" encoding="UTF-8"?>
<env:envelope xmlns:env="http://marklogic.com/data-hub/envelope"><env:headers><env:id>4a1e088d-c694-428b-9e08-8dc694828b66</env:id><env:glossaryName>IVOAT</env:glossaryName><env:timestamp>2019-09-23T20:54:46.878-04:00</env:timestamp></env:headers><env:instance><skos:Concept xmlns:rdf="http://www.w3.org/1999/02/22-rdf-syntax-ns#" xmlns:skos="http://www.w3.org/2008/05/skos#" rdf:about="#asteroid">
		<skos:inScheme rdf:resource=""/>
		<skos:prefLabel>asteroid</skos:prefLabel>
		<skos:definition>asteroid</skos:definition>
		<skos:altLabel>minor planet</skos:altLabel>
		<skos:altLabel>planetoid</skos:altLabel>
		<skos:broader rdf:resource="#rotatingBody"/>
		<skos:narrower rdf:resource="#nearEarthAsteroid"/>
		<skos:related rdf:resource="#EdgeworthKuiperBelt"/>
		<skos:related rdf:resource="#KirkwoodGap"/>
		<skos:related rdf:resource="#SolarSystem"/>
		<skos:related rdf:resource="#asteroidBelt"/>
		<skos:related rdf:resource="#asteroidOccultation"/>
		<skos:related rdf:resource="#interplanetaryMatter"/>
		<skos:related rdf:resource="#meteorStream"/>
		<skos:related rdf:resource="#meteorite"/>
		<skos:related rdf:resource="#meteoroidDustCloud"/>
		<skos:related rdf:resource="#meteoroid"/>
		<skos:related rdf:resource="#minorPlanetFamily"/>
		<skos:related rdf:resource="#planetesimal"/>
		<skos:related rdf:resource="#resonanceGap"/>
		<skos:related rdf:resource="#transNeptunianObject"/>
	</skos:Concept></env:instance></env:envelope>