<?xml version="1.0" encoding="UTF-8"?>
<env:envelope xmlns:env="http://marklogic.com/data-hub/envelope"><env:headers><env:id>b1d73b65-ab36-40a0-973b-65ab36c0a083</env:id><env:glossaryName>IVOAT</env:glossaryName><env:timestamp>2019-09-23T20:54:46.878-04:00</env:timestamp></env:headers><env:instance><skos:Concept xmlns:rdf="http://www.w3.org/1999/02/22-rdf-syntax-ns#" xmlns:skos="http://www.w3.org/2008/05/skos#" rdf:about="#WilsonBappuEffect">
		<skos:inScheme rdf:resource=""/>
		<skos:prefLabel>Wilson-Bappu effect</skos:prefLabel>
		<skos:definition>Wilson-Bappu effect</skos:definition>
		<skos:altLabel>Wilson Bappu effect</skos:altLabel>
		<skos:related rdf:resource="#CaIiEmissionLine"/>
		<skos:related rdf:resource="#KLine"/>
		<skos:related rdf:resource="#absoluteMagnitude"/>
		<skos:related rdf:resource="#lateTypeStar"/>
	</skos:Concept></env:instance></env:envelope>